pchime/__init__.py
pchime/__main__.py
pchime/helpers/help_menu.py
pchime/initiate_federated_learning/client/client_node.py
pchime/initiate_federated_learning/server/server_node.py
pchime/local_data_instances/create_data_instance.py
pchime/local_data_instances/fresh_installation_conditions/create_storage_blob_directory.py
pchime/local_data_instances/load_data_files/load_csv_file.py
pchime-0.1.0.dist-info/licenses/LICENSE
pchime-0.1.0.dist-info/METADATA
pchime-0.1.0.dist-info/WHEEL
pchime-0.1.0.dist-info/entry_points.txt
pchime-0.1.0.dist-info/top_level.txt
pchime-0.1.0.dist-info/RECORD
