Metadata-Version: 2.4
Name: pchime
Version: 0.1.0
Summary: Federated learning support mechanism
Author: Vignesh T D
Requires-Python: >=3.8
License-File: LICENSE
Requires-Dist: flwr>=1.23.0
Requires-Dist: numpy
Requires-Dist: pandas
Requires-Dist: rich
Requires-Dist: scikit_learn
Dynamic: license-file
